{
  "player": "Elena Rybakina",
  "aces_l5": 5.1,
  "aces_l10": 5.08,
  "aces_season": 5.0,
  "aces_std": 2.5,
  "breakpoints_won_l5": 3.6,
  "breakpoints_won_l10": 3.58,
  "breakpoints_won_season": 3.5,
  "breakpoints_won_std": 1.5,
  "games_won_l5": 12.2,
  "games_won_l10": 12.15,
  "games_won_season": 12.0,
  "games_won_std": 3.0,
  "fantasy_score_l5": 25.5,
  "fantasy_score_l10": 25.4,
  "fantasy_score_season": 25.0,
  "fantasy_score_std": 8.0,
  "total_games_l5": 22.3,
  "total_games_l10": 22.2,
  "total_games_season": 22.0,
  "total_games_std": 4.0,
  "double_faults_l5": 2.55,
  "double_faults_l10": 2.54,
  "double_faults_season": 2.5,
  "double_faults_std": 1.5,
  "tiebreakers_l5": 0.8200000000000001,
  "tiebreakers_l10": 0.8150000000000001,
  "tiebreakers_season": 0.8,
  "tiebreakers_std": 0.6,
  "sets_won_l5": 1.53,
  "sets_won_l10": 1.52,
  "sets_won_season": 1.5,
  "sets_won_std": 0.8,
  "sets_played_l5": 2.52,
  "sets_played_l10": 2.515,
  "sets_played_season": 2.5,
  "sets_played_std": 0.5,
  "surface": "Hard",
  "surface_adjustment": 1.0,
  "opponent_strength": 1.0,
  "matches_played": 10,
  "last_updated": "2026-01-31T02:26:04.030470"
}