{
  "plays": [
    {
      "player": "Pascal Siakam",
      "team": "IND",
      "opponent": "UNK",
      "stat": "assists",
      "line": 2.5,
      "league": "NBA",
      "goblin": true,
      "direction": "higher"
    },
    {
      "player": "Jalen Johnson",
      "team": "ATL",
      "opponent": "IND",
      "stat": "pra",
      "line": 43.5,
      "league": "NBA",
      "direction": "higher"
    },
    {
      "player": "Jalen Johnson",
      "team": "ATL",
      "opponent": "IND",
      "stat": "pra",
      "line": 43.5,
      "league": "NBA",
      "direction": "lower"
    },
    {
      "player": "Pascal Siakam",
      "team": "IND",
      "opponent": "UNK",
      "stat": "pra",
      "line": 35.5,
      "league": "NBA",
      "direction": "higher"
    },
    {
      "player": "Pascal Siakam",
      "team": "IND",
      "opponent": "UNK",
      "stat": "pra",
      "line": 35.5,
      "league": "NBA",
      "direction": "lower"
    },
    {
      "player": "Jalen Johnson",
      "team": "ATL",
      "opponent": "IND",
      "stat": "reb+ast",
      "line": 19.0,
      "league": "NBA",
      "direction": "higher"
    },
    {
      "player": "Jalen Johnson",
      "team": "ATL",
      "opponent": "IND",
      "stat": "reb+ast",
      "line": 19.0,
      "league": "NBA",
      "direction": "lower"
    },
    {
      "player": "Dyson Daniels",
      "team": "ATL",
      "opponent": "IND",
      "stat": "rebounds",
      "line": 7.0,
      "league": "NBA",
      "direction": "higher"
    },
    {
      "player": "Dyson Daniels",
      "team": "ATL",
      "opponent": "IND",
      "stat": "rebounds",
      "line": 7.0,
      "league": "NBA",
      "direction": "lower"
    },
    {
      "player": "Onyeka Okongwu",
      "team": "ATL",
      "opponent": "IND",
      "stat": "points",
      "line": 17.0,
      "league": "NBA",
      "direction": "higher"
    },
    {
      "player": "Onyeka Okongwu",
      "team": "ATL",
      "opponent": "IND",
      "stat": "points",
      "line": 17.0,
      "league": "NBA",
      "direction": "lower"
    },
    {
      "player": "vs IND Nickeil Alexander-Walker",
      "team": "ATL",
      "opponent": "IND",
      "stat": "3pm",
      "line": 2.5,
      "league": "NBA",
      "goblin": true,
      "direction": "higher"
    },
    {
      "player": "Aaron Nesmith",
      "team": "IND",
      "opponent": "UNK",
      "stat": "3pm",
      "line": 1.5,
      "league": "NBA",
      "goblin": true,
      "direction": "higher"
    },
    {
      "player": "CJ McCollum",
      "team": "ATL",
      "opponent": "IND",
      "stat": "3pm",
      "line": 1.5,
      "league": "NBA",
      "goblin": true,
      "direction": "higher"
    },
    {
      "player": "Jalen Johnson",
      "team": "ATL",
      "opponent": "IND",
      "stat": "3pm",
      "line": 1.5,
      "league": "NBA",
      "direction": "higher"
    },
    {
      "player": "Jalen Johnson",
      "team": "ATL",
      "opponent": "IND",
      "stat": "3pm",
      "line": 1.5,
      "league": "NBA",
      "direction": "lower"
    },
    {
      "player": "Onyeka Okongwu",
      "team": "ATL",
      "opponent": "IND",
      "stat": "3pm",
      "line": 1.5,
      "league": "NBA",
      "goblin": true,
      "direction": "higher"
    },
    {
      "player": "Andrew Nembhard",
      "team": "IND",
      "opponent": "UNK",
      "stat": "3pm",
      "line": 1.5,
      "league": "NBA",
      "direction": "higher"
    },
    {
      "player": "Andrew Nembhard",
      "team": "IND",
      "opponent": "UNK",
      "stat": "3pm",
      "line": 1.5,
      "league": "NBA",
      "direction": "lower"
    },
    {
      "player": "Jarace Walker",
      "team": "IND",
      "opponent": "UNK",
      "stat": "3pm",
      "line": 1.5,
      "league": "NBA",
      "direction": "higher"
    },
    {
      "player": "Jarace Walker",
      "team": "IND",
      "opponent": "UNK",
      "stat": "3pm",
      "line": 1.5,
      "league": "NBA",
      "direction": "lower"
    },
    {
      "player": "Pascal Siakam",
      "team": "IND",
      "opponent": "UNK",
      "stat": "3pm",
      "line": 3.5,
      "league": "NBA",
      "demon": true,
      "direction": "higher"
    },
    {
      "player": "Bennedict Mathurin",
      "team": "IND",
      "opponent": "UNK",
      "stat": "3pm",
      "line": 0.5,
      "league": "NBA",
      "goblin": true,
      "direction": "higher"
    },
    {
      "player": "Luke Kennard",
      "team": "ATL",
      "opponent": "IND",
      "stat": "3pm",
      "line": 0.5,
      "league": "NBA",
      "goblin": true,
      "direction": "higher"
    },
    {
      "player": "Corey Kispert",
      "team": "ATL",
      "opponent": "IND",
      "stat": "3pm",
      "line": 0.5,
      "league": "NBA",
      "goblin": true,
      "direction": "higher"
    },
    {
      "player": "Ben Sheppard",
      "team": "IND",
      "opponent": "UNK",
      "stat": "3pm",
      "line": 0.5,
      "league": "NBA",
      "goblin": true,
      "direction": "higher"
    },
    {
      "player": "Johnny Furphy",
      "team": "IND",
      "opponent": "UNK",
      "stat": "3pm",
      "line": 1.5,
      "league": "NBA",
      "demon": true,
      "direction": "higher"
    },
    {
      "player": "Dyson Daniels",
      "team": "ATL",
      "opponent": "IND",
      "stat": "3pm",
      "line": 0.5,
      "league": "NBA",
      "demon": true,
      "direction": "higher"
    },
    {
      "player": "T.J. McConnell",
      "team": "IND",
      "opponent": "UNK",
      "stat": "3pm",
      "line": 0.5,
      "league": "NBA",
      "demon": true,
      "direction": "higher"
    },
    {
      "player": "T.J. McConnell",
      "team": "IND",
      "opponent": "UNK",
      "stat": "3pm",
      "line": 0.5,
      "league": "NBA",
      "demon": true,
      "direction": "lower"
    },
    {
      "player": "MoreJalen Johnson",
      "team": "ATL",
      "opponent": "IND",
      "stat": "assists",
      "line": 7.5,
      "league": "NBA",
      "direction": "higher"
    },
    {
      "player": "MoreJalen Johnson",
      "team": "ATL",
      "opponent": "IND",
      "stat": "assists",
      "line": 7.5,
      "league": "NBA",
      "direction": "lower"
    },
    {
      "player": "Andrew Nembhard",
      "team": "IND",
      "opponent": "UNK",
      "stat": "assists",
      "line": 6.5,
      "league": "NBA",
      "goblin": true,
      "direction": "higher"
    },
    {
      "player": "Dyson Daniels",
      "team": "ATL",
      "opponent": "IND",
      "stat": "assists",
      "line": 6.0,
      "league": "NBA",
      "direction": "higher"
    },
    {
      "player": "Dyson Daniels",
      "team": "ATL",
      "opponent": "IND",
      "stat": "assists",
      "line": 6.0,
      "league": "NBA",
      "direction": "lower"
    },
    {
      "player": "T.J. McConnell",
      "team": "IND",
      "opponent": "UNK",
      "stat": "assists",
      "line": 4.5,
      "league": "NBA",
      "direction": "higher"
    },
    {
      "player": "T.J. McConnell",
      "team": "IND",
      "opponent": "UNK",
      "stat": "assists",
      "line": 4.5,
      "league": "NBA",
      "direction": "lower"
    },
    {
      "player": "Pascal Siakam",
      "team": "IND",
      "opponent": "UNK",
      "stat": "assists",
      "line": 2.5,
      "league": "NBA",
      "goblin": true,
      "direction": "higher"
    },
    {
      "player": "Nickeil Alexander-Walker",
      "team": "ATL",
      "opponent": "IND",
      "stat": "assists",
      "line": 3.5,
      "league": "NBA",
      "direction": "higher"
    },
    {
      "player": "Nickeil Alexander-Walker",
      "team": "ATL",
      "opponent": "IND",
      "stat": "assists",
      "line": 3.5,
      "league": "NBA",
      "direction": "lower"
    },
    {
      "player": "CJ McCollum",
      "team": "ATL",
      "opponent": "IND",
      "stat": "assists",
      "line": 2.5,
      "league": "NBA",
      "goblin": true,
      "direction": "higher"
    },
    {
      "player": "Onyeka Okongwu",
      "team": "ATL",
      "opponent": "IND",
      "stat": "assists",
      "line": 2.5,
      "league": "NBA",
      "goblin": true,
      "direction": "higher"
    },
    {
      "player": "Luke Kennard",
      "team": "ATL",
      "opponent": "IND",
      "stat": "assists",
      "line": 1.5,
      "league": "NBA",
      "goblin": true,
      "direction": "higher"
    },
    {
      "player": "Aaron Nesmith",
      "team": "IND",
      "opponent": "UNK",
      "stat": "assists",
      "line": 1.5,
      "league": "NBA",
      "goblin": true,
      "direction": "higher"
    },
    {
      "player": "Bennedict Mathurin",
      "team": "IND",
      "opponent": "UNK",
      "stat": "assists",
      "line": 1.5,
      "league": "NBA",
      "direction": "higher"
    },
    {
      "player": "Bennedict Mathurin",
      "team": "IND",
      "opponent": "UNK",
      "stat": "assists",
      "line": 1.5,
      "league": "NBA",
      "direction": "lower"
    },
    {
      "player": "Jarace Walker",
      "team": "IND",
      "opponent": "UNK",
      "stat": "assists",
      "line": 1.5,
      "league": "NBA",
      "goblin": true,
      "direction": "higher"
    },
    {
      "player": "Corey Kispert",
      "team": "ATL",
      "opponent": "IND",
      "stat": "assists",
      "line": 0.5,
      "league": "NBA",
      "goblin": true,
      "direction": "higher"
    },
    {
      "player": "Ben Sheppard",
      "team": "IND",
      "opponent": "UNK",
      "stat": "assists",
      "line": 0.5,
      "league": "NBA",
      "goblin": true,
      "direction": "higher"
    },
    {
      "player": "Johnny Furphy",
      "team": "IND",
      "opponent": "UNK",
      "stat": "assists",
      "line": 0.5,
      "league": "NBA",
      "goblin": true,
      "direction": "higher"
    },
    {
      "player": "Johnny Furphy",
      "team": "IND",
      "opponent": "UNK",
      "stat": "assists",
      "line": 0.5,
      "league": "NBA",
      "goblin": true,
      "direction": "lower"
    },
    {
      "player": "Luke Kennard",
      "team": "ATL",
      "opponent": "IND",
      "stat": "pra",
      "line": 43.5,
      "league": "NBA",
      "direction": "higher"
    },
    {
      "player": "Luke Kennard",
      "team": "ATL",
      "opponent": "IND",
      "stat": "pra",
      "line": 43.5,
      "league": "NBA",
      "direction": "lower"
    },
    {
      "player": "Pascal Siakam",
      "team": "IND",
      "opponent": "UNK",
      "stat": "pra",
      "line": 35.5,
      "league": "NBA",
      "direction": "higher"
    },
    {
      "player": "Pascal Siakam",
      "team": "IND",
      "opponent": "UNK",
      "stat": "pra",
      "line": 35.5,
      "league": "NBA",
      "direction": "lower"
    },
    {
      "player": "Andrew Nembhard",
      "team": "IND",
      "opponent": "UNK",
      "stat": "pra",
      "line": 27.5,
      "league": "NBA",
      "direction": "higher"
    },
    {
      "player": "Andrew Nembhard",
      "team": "IND",
      "opponent": "UNK",
      "stat": "pra",
      "line": 27.5,
      "league": "NBA",
      "direction": "lower"
    },
    {
      "player": "Onyeka Okongwu",
      "team": "ATL",
      "opponent": "IND",
      "stat": "pra",
      "line": 29.5,
      "league": "NBA",
      "direction": "higher"
    },
    {
      "player": "Onyeka Okongwu",
      "team": "ATL",
      "opponent": "IND",
      "stat": "pra",
      "line": 29.5,
      "league": "NBA",
      "direction": "lower"
    },
    {
      "player": "Dyson Daniels",
      "team": "ATL",
      "opponent": "IND",
      "stat": "pra",
      "line": 24.5,
      "league": "NBA",
      "direction": "higher"
    },
    {
      "player": "Dyson Daniels",
      "team": "ATL",
      "opponent": "IND",
      "stat": "pra",
      "line": 24.5,
      "league": "NBA",
      "direction": "lower"
    },
    {
      "player": "Nickeil Alexander-Walker",
      "team": "ATL",
      "opponent": "IND",
      "stat": "pra",
      "line": 27.5,
      "league": "NBA",
      "direction": "higher"
    },
    {
      "player": "Nickeil Alexander-Walker",
      "team": "ATL",
      "opponent": "IND",
      "stat": "pra",
      "line": 27.5,
      "league": "NBA",
      "direction": "lower"
    },
    {
      "player": "CJ McCollum",
      "team": "ATL",
      "opponent": "IND",
      "stat": "pra",
      "line": 23.5,
      "league": "NBA",
      "direction": "higher"
    },
    {
      "player": "CJ McCollum",
      "team": "ATL",
      "opponent": "IND",
      "stat": "pra",
      "line": 23.5,
      "league": "NBA",
      "direction": "lower"
    },
    {
      "player": "Aaron Nesmith",
      "team": "IND",
      "opponent": "UNK",
      "stat": "pra",
      "line": 20.5,
      "league": "NBA",
      "direction": "higher"
    },
    {
      "player": "Aaron Nesmith",
      "team": "IND",
      "opponent": "UNK",
      "stat": "pra",
      "line": 20.5,
      "league": "NBA",
      "direction": "lower"
    },
    {
      "player": "Bennedict Mathurin",
      "team": "IND",
      "opponent": "UNK",
      "stat": "pra",
      "line": 20.5,
      "league": "NBA",
      "direction": "higher"
    },
    {
      "player": "Bennedict Mathurin",
      "team": "IND",
      "opponent": "UNK",
      "stat": "pra",
      "line": 20.5,
      "league": "NBA",
      "direction": "lower"
    },
    {
      "player": "Jarace Walker",
      "team": "IND",
      "opponent": "UNK",
      "stat": "pra",
      "line": 17.5,
      "league": "NBA",
      "direction": "higher"
    },
    {
      "player": "Jarace Walker",
      "team": "IND",
      "opponent": "UNK",
      "stat": "pra",
      "line": 17.5,
      "league": "NBA",
      "direction": "lower"
    },
    {
      "player": "T.J. McConnell",
      "team": "IND",
      "opponent": "UNK",
      "stat": "pra",
      "line": 15.5,
      "league": "NBA",
      "direction": "higher"
    },
    {
      "player": "T.J. McConnell",
      "team": "IND",
      "opponent": "UNK",
      "stat": "pra",
      "line": 15.5,
      "league": "NBA",
      "direction": "lower"
    },
    {
      "player": "Corey Kispert",
      "team": "ATL",
      "opponent": "IND",
      "stat": "pra",
      "line": 11.5,
      "league": "NBA",
      "direction": "higher"
    },
    {
      "player": "Corey Kispert",
      "team": "ATL",
      "opponent": "IND",
      "stat": "pra",
      "line": 11.5,
      "league": "NBA",
      "direction": "lower"
    },
    {
      "player": "Johnny Furphy",
      "team": "IND",
      "opponent": "UNK",
      "stat": "pra",
      "line": 11.5,
      "league": "NBA",
      "direction": "higher"
    },
    {
      "player": "Johnny Furphy",
      "team": "IND",
      "opponent": "UNK",
      "stat": "pra",
      "line": 11.5,
      "league": "NBA",
      "direction": "lower"
    },
    {
      "player": "Luke Kennard",
      "team": "ATL",
      "opponent": "IND",
      "stat": "pra",
      "line": 9.5,
      "league": "NBA",
      "goblin": true,
      "direction": "higher"
    },
    {
      "player": "Ben Sheppard",
      "team": "IND",
      "opponent": "UNK",
      "stat": "pra",
      "line": 7.5,
      "league": "NBA",
      "direction": "lower"
    },
    {
      "player": "MoPascal Siakam",
      "team": "IND",
      "opponent": "UNK",
      "stat": "points",
      "line": 23.5,
      "league": "NBA",
      "direction": "higher"
    },
    {
      "player": "MoPascal Siakam",
      "team": "IND",
      "opponent": "UNK",
      "stat": "points",
      "line": 23.5,
      "league": "NBA",
      "direction": "lower"
    },
    {
      "player": "Jalen Johnson",
      "team": "ATL",
      "opponent": "IND",
      "stat": "points",
      "line": 24.5,
      "league": "NBA",
      "direction": "higher"
    },
    {
      "player": "Jalen Johnson",
      "team": "ATL",
      "opponent": "IND",
      "stat": "points",
      "line": 24.5,
      "league": "NBA",
      "direction": "lower"
    },
    {
      "player": "Nickeil Alexander-Walker",
      "team": "ATL",
      "opponent": "IND",
      "stat": "points",
      "line": 19.5,
      "league": "NBA",
      "direction": "higher"
    },
    {
      "player": "Nickeil Alexander-Walker",
      "team": "ATL",
      "opponent": "IND",
      "stat": "points",
      "line": 19.5,
      "league": "NBA",
      "direction": "lower"
    },
    {
      "player": "CJ McCollum",
      "team": "ATL",
      "opponent": "IND",
      "stat": "points",
      "line": 17.5,
      "league": "NBA",
      "direction": "higher"
    },
    {
      "player": "CJ McCollum",
      "team": "ATL",
      "opponent": "IND",
      "stat": "points",
      "line": 17.5,
      "league": "NBA",
      "direction": "lower"
    },
    {
      "player": "Onyeka Okongwu",
      "team": "ATL",
      "opponent": "IND",
      "stat": "points",
      "line": 17.0,
      "league": "NBA",
      "direction": "higher"
    },
    {
      "player": "Onyeka Okongwu",
      "team": "ATL",
      "opponent": "IND",
      "stat": "points",
      "line": 17.0,
      "league": "NBA",
      "direction": "lower"
    },
    {
      "player": "Andrew Nembhard",
      "team": "IND",
      "opponent": "UNK",
      "stat": "points",
      "line": 16.5,
      "league": "NBA",
      "direction": "higher"
    },
    {
      "player": "Andrew Nembhard",
      "team": "IND",
      "opponent": "UNK",
      "stat": "points",
      "line": 16.5,
      "league": "NBA",
      "direction": "lower"
    },
    {
      "player": "Bennedict Mathurin",
      "team": "IND",
      "opponent": "UNK",
      "stat": "points",
      "line": 14.5,
      "league": "NBA",
      "direction": "higher"
    },
    {
      "player": "Bennedict Mathurin",
      "team": "IND",
      "opponent": "UNK",
      "stat": "points",
      "line": 14.5,
      "league": "NBA",
      "direction": "lower"
    },
    {
      "player": "Aaron Nesmith",
      "team": "IND",
      "opponent": "UNK",
      "stat": "points",
      "line": 13.5,
      "league": "NBA",
      "direction": "higher"
    },
    {
      "player": "Aaron Nesmith",
      "team": "IND",
      "opponent": "UNK",
      "stat": "points",
      "line": 13.5,
      "league": "NBA",
      "direction": "lower"
    },
    {
      "player": "Dyson Daniels",
      "team": "ATL",
      "opponent": "IND",
      "stat": "points",
      "line": 11.5,
      "league": "NBA",
      "direction": "higher"
    },
    {
      "player": "Dyson Daniels",
      "team": "ATL",
      "opponent": "IND",
      "stat": "points",
      "line": 11.5,
      "league": "NBA",
      "direction": "lower"
    },
    {
      "player": "Jarace Walker",
      "team": "IND",
      "opponent": "UNK",
      "stat": "points",
      "line": 10.5,
      "league": "NBA",
      "direction": "higher"
    },
    {
      "player": "Jarace Walker",
      "team": "IND",
      "opponent": "UNK",
      "stat": "points",
      "line": 10.5,
      "league": "NBA",
      "direction": "lower"
    },
    {
      "player": "Corey Kispert",
      "team": "ATL",
      "opponent": "IND",
      "stat": "points",
      "line": 7.5,
      "league": "NBA",
      "direction": "higher"
    },
    {
      "player": "Corey Kispert",
      "team": "ATL",
      "opponent": "IND",
      "stat": "points",
      "line": 7.5,
      "league": "NBA",
      "direction": "lower"
    },
    {
      "player": "T.J. McConnell",
      "team": "IND",
      "opponent": "UNK",
      "stat": "points",
      "line": 8.5,
      "league": "NBA",
      "direction": "higher"
    },
    {
      "player": "T.J. McConnell",
      "team": "IND",
      "opponent": "UNK",
      "stat": "points",
      "line": 8.5,
      "league": "NBA",
      "direction": "lower"
    },
    {
      "player": "Johnny Furphy",
      "team": "IND",
      "opponent": "UNK",
      "stat": "points",
      "line": 5.5,
      "league": "NBA",
      "direction": "higher"
    },
    {
      "player": "Johnny Furphy",
      "team": "IND",
      "opponent": "UNK",
      "stat": "points",
      "line": 5.5,
      "league": "NBA",
      "direction": "lower"
    },
    {
      "player": "Luke Kennard",
      "team": "ATL",
      "opponent": "IND",
      "stat": "points",
      "line": 7.5,
      "league": "NBA",
      "direction": "higher"
    },
    {
      "player": "Luke Kennard",
      "team": "ATL",
      "opponent": "IND",
      "stat": "points",
      "line": 7.5,
      "league": "NBA",
      "direction": "lower"
    },
    {
      "player": "Ben Sheppard",
      "team": "IND",
      "opponent": "UNK",
      "stat": "points",
      "line": 3.5,
      "league": "NBA",
      "direction": "higher"
    },
    {
      "player": "Ben Sheppard",
      "team": "IND",
      "opponent": "UNK",
      "stat": "points",
      "line": 3.5,
      "league": "NBA",
      "direction": "lower"
    }
  ],
  "raw_lines": [
    "Pascal SiakamGoblin",
    "IND - F",
    "Pascal Siakam",
    "@ ATL 27m 21s",
    "Swap",
    "2.5",
    "Assists",
    "More",
    "Trending",
    "14.8K",
    "Jalen Johnson",
    "ATL - F",
    "Jalen Johnson",
    "vs IND 27m 21s",
    "43.5",
    "PRA",
    "Less",
    "More",
    "Trending",
    "11.7K",
    "Pascal Siakam",
    "IND - F",
    "Pascal Siakam",
    "@ ATL 27m 21s",
    "35.5",
    "PRA",
    "Less",
    "More",
    "Trending",
    "11.4K",
    "Jalen Johnson",
    "ATL - F",
    "Jalen Johnson",
    "vs IND 27m 21s",
    "19",
    "Rebs+Asts",
    "Less",
    "More",
    "Trending",
    "10.0K",
    "Dyson Daniels",
    "ATL - G",
    "Dyson Daniels",
    "vs IND 27m 21s",
    "7",
    "Rebounds",
    "Less",
    "More",
    "Trending",
    "8.3K",
    "Onyeka Okongwu",
    "ATL - F-C",
    "Onyeka Okongwu",
    "vs IND 27m 21s",
    "17",
    "Points",
    "Less",
    "More",
    "Trending",
    "7.7K",
    "Jalen Johnson",
    "ATL - F",
    "Jalen Johnson",
    "vs IND Nickeil Alexander-WalkerGoblin",
    "ATL - G",
    "Nickeil Alexander-Walker",
    "vs IND 27m 0s",
    "2.5",
    "3PTM",
    "More",
    "Aaron NesmithGoblin",
    "IND - G-F",
    "Aaron Nesmith",
    "@ ATL 27m 0s",
    "1.5",
    "3PTM",
    "More",
    "CJ McCollumGoblin",
    "ATL - G",
    "CJ McCollum",
    "vs IND 27m 0s",
    "1.5",
    "3PTM",
    "More",
    "Jalen Johnson",
    "ATL - F",
    "Jalen Johnson",
    "vs IND 27m 0s",
    "1.5",
    "3PTM",
    "Less",
    "More",
    "Onyeka OkongwuGoblin",
    "ATL - F-C",
    "Onyeka Okongwu",
    "vs IND 27m 0s",
    "1.5",
    "3PTM",
    "More",
    "Andrew Nembhard",
    "IND - G-F",
    "Andrew Nembhard",
    "@ ATL 27m 0s",
    "1.5",
    "3PTM",
    "Less",
    "More",
    "Jarace Walker",
    "IND - F",
    "Jarace Walker",
    "@ ATL 27m 0s",
    "1.5",
    "3PTM",
    "Less",
    "More",
    "Pascal SiakamDemon",
    "IND - F",
    "Pascal Siakam",
    "@ ATL 27m 0s",
    "3.5",
    "3PTM",
    "More",
    "Bennedict MathurinGoblin",
    "IND - G-F",
    "Bennedict Mathurin",
    "@ ATL 27m 0s",
    "0.5",
    "3PTM",
    "More",
    "Luke KennardGoblin",
    "ATL - G",
    "Luke Kennard",
    "vs IND 27m 0s",
    "0.5",
    "3PTM",
    "More",
    "Corey KispertGoblin",
    "ATL - F",
    "Corey Kispert",
    "vs IND 27m 0s",
    "0.5",
    "3PTM",
    "More",
    "Ben SheppardGoblin",
    "IND - G",
    "Ben Sheppard",
    "@ ATL 27m 0s",
    "0.5",
    "3PTM",
    "More",
    "Johnny FurphyDemon",
    "IND - G",
    "Johnny Furphy",
    "@ ATL 27m 0s",
    "1.5",
    "3PTM",
    "More",
    "Dyson DanielsDemon",
    "ATL - G",
    "Dyson Daniels",
    "vs IND 27m 0s",
    "0.5",
    "3PTM",
    "More",
    "T.J. McConnellDemon",
    "IND - G",
    "T.J. McConnell",
    "@ ATL 27m 0s",
    "0.5",
    "3PTM",
    "MoreJalen Johnson",
    "ATL - F",
    "Jalen Johnson",
    "vs IND 26m 38s",
    "7.5",
    "Assists",
    "Less",
    "More",
    "Andrew NembhardGoblin",
    "IND - G-F",
    "Andrew Nembhard",
    "@ ATL 26m 38s",
    "6.5",
    "Assists",
    "More",
    "Dyson Daniels",
    "ATL - G",
    "Dyson Daniels",
    "vs IND 26m 38s",
    "6",
    "Assists",
    "Less",
    "More",
    "T.J. McConnell",
    "IND - G",
    "T.J. McConnell",
    "@ ATL 26m 38s",
    "4.5",
    "Assists",
    "Less",
    "More",
    "Trending",
    "25.2K",
    "Pascal SiakamGoblin",
    "IND - F",
    "Pascal Siakam",
    "@ ATL 26m 38s",
    "2.5",
    "Assists",
    "More",
    "Nickeil Alexander-Walker",
    "ATL - G",
    "Nickeil Alexander-Walker",
    "vs IND 26m 38s",
    "3.5",
    "Assists",
    "Less",
    "More",
    "CJ McCollumGoblin",
    "ATL - G",
    "CJ McCollum",
    "vs IND 26m 38s",
    "2.5",
    "Assists",
    "More",
    "Onyeka OkongwuGoblin",
    "ATL - F-C",
    "Onyeka Okongwu",
    "vs IND 26m 38s",
    "2.5",
    "Assists",
    "More",
    "Luke KennardGoblin",
    "ATL - G",
    "Luke Kennard",
    "vs IND 26m 38s",
    "1.5",
    "Assists",
    "More",
    "Aaron NesmithGoblin",
    "IND - G-F",
    "Aaron Nesmith",
    "@ ATL 26m 38s",
    "1.5",
    "Assists",
    "More",
    "Bennedict Mathurin",
    "IND - G-F",
    "Bennedict Mathurin",
    "@ ATL 26m 38s",
    "1.5",
    "Assists",
    "Less",
    "More",
    "Jarace WalkerGoblin",
    "IND - F",
    "Jarace Walker",
    "@ ATL 26m 38s",
    "1.5",
    "Assists",
    "More",
    "Corey KispertGoblin",
    "ATL - F",
    "Corey Kispert",
    "vs IND 26m 38s",
    "0.5",
    "Assists",
    "More",
    "Ben SheppardGoblin",
    "IND - G",
    "Ben Sheppard",
    "@ ATL 26m 38s",
    "0.5",
    "Assists",
    "More",
    "Johnny FurphyGoblin",
    "IND - G",
    "Johnny Furphy",
    "@ ATL 26m 38s",
    "0.5",
    "Assists",
    "CJ McCollum",
    "ATL - G",
    "CJ McCollum",
    "vs IND 26m 24s",
    "6.5",
    "FG Made",
    "Less",
    "More",
    "Nickeil Alexander-WalkerGoblin",
    "ATL - G",
    "Nickeil Alexander-Walker",
    "vs IND 26m 24s",
    "6.5",
    "FG Made",
    "More",
    "Dyson DanielsDemon",
    "ATL - G",
    "Dyson Daniels",
    "vs IND 26m 24s",
    "5.5",
    "FG Made",
    "More",
    "Aaron Nesmith",
    "IND - G-F",
    "Aaron Nesmith",
    "@ ATL 26m 24s",
    "4.5",
    "FG Made",
    "Less",
    "More",
    "Luke Kennard",
    "ATL - G",
    "Luke Kennard",
    "vs IND 26m 24s",
    "2.5",
    "FG Made",
    "Less",
    "MoreCJ McCollum",
    "ATL - G",
    "CJ McCollum",
    "vs IND 26m 24s",
    "6.5",
    "FG Made",
    "Less",
    "More",
    "Nickeil Alexander-WalkerGoblin",
    "ATL - G",
    "Nickeil Alexander-Walker",
    "vs IND 26m 24s",
    "6.5",
    "FG Made",
    "More",
    "Dyson DanielsDemon",
    "ATL - G",
    "Dyson Daniels",
    "vs IND 26m 24s",
    "5.5",
    "FG Made",
    "More",
    "Aaron Nesmith",
    "IND - G-F",
    "Aaron Nesmith",
    "@ ATL 26m 24s",
    "4.5",
    "FG Made",
    "Less",
    "More",
    "Luke Kennard",
    "ATL - G",
    "Luke Kennard",
    "vs IND 26m 24s",
    "2.5",
    "FG Made",
    "Less",
    "MoreJalen Johnson",
    "vs IND 26m 7s",
    "43.5",
    "PRA",
    "Less",
    "More",
    "Trending",
    "11.7K",
    "Pascal Siakam",
    "IND - F",
    "Pascal Siakam",
    "@ ATL 26m 7s",
    "35.5",
    "PRA",
    "Less",
    "More",
    "Andrew Nembhard",
    "IND - G-F",
    "Andrew Nembhard",
    "@ ATL 26m 7s",
    "27.5",
    "PRA",
    "Less",
    "More",
    "Onyeka Okongwu",
    "ATL - F-C",
    "Onyeka Okongwu",
    "vs IND 26m 7s",
    "29.5",
    "PRA",
    "Less",
    "More",
    "Dyson Daniels",
    "ATL - G",
    "Dyson Daniels",
    "vs IND 26m 7s",
    "24.5",
    "PRA",
    "Less",
    "More",
    "Nickeil Alexander-Walker",
    "ATL - G",
    "Nickeil Alexander-Walker",
    "vs IND 26m 7s",
    "27.5",
    "PRA",
    "Less",
    "More",
    "CJ McCollum",
    "ATL - G",
    "CJ McCollum",
    "vs IND 26m 7s",
    "23.5",
    "PRA",
    "Less",
    "More",
    "Aaron Nesmith",
    "IND - G-F",
    "Aaron Nesmith",
    "@ ATL 26m 7s",
    "20.5",
    "PRA",
    "Less",
    "More",
    "Bennedict Mathurin",
    "IND - G-F",
    "Bennedict Mathurin",
    "@ ATL 26m 7s",
    "20.5",
    "PRA",
    "Less",
    "More",
    "Jarace Walker",
    "IND - F",
    "Jarace Walker",
    "@ ATL 26m 7s",
    "17.5",
    "PRA",
    "Less",
    "More",
    "T.J. McConnell",
    "IND - G",
    "T.J. McConnell",
    "@ ATL 26m 7s",
    "15.5",
    "PRA",
    "Less",
    "More",
    "Corey Kispert",
    "ATL - F",
    "Corey Kispert",
    "vs IND 26m 7s",
    "11.5",
    "PRA",
    "Less",
    "More",
    "Johnny Furphy",
    "IND - G",
    "Johnny Furphy",
    "@ ATL 26m 7s",
    "11.5",
    "PRA",
    "Less",
    "More",
    "Luke KennardGoblin",
    "ATL - G",
    "Luke Kennard",
    "vs IND 26m 7s",
    "9.5",
    "PRA",
    "More",
    "Ben Sheppard",
    "IND - G",
    "Ben Sheppard",
    "@ ATL 26m 7s",
    "7.5",
    "PRA",
    "Less",
    "MoPascal Siakam",
    "IND - F",
    "Pascal Siakam",
    "@ ATL 25m 54s",
    "23.5",
    "Points",
    "Less",
    "More",
    "Jalen Johnson",
    "ATL - F",
    "Jalen Johnson",
    "vs IND 25m 54s",
    "24.5",
    "Points",
    "Less",
    "More",
    "Nickeil Alexander-Walker",
    "ATL - G",
    "Nickeil Alexander-Walker",
    "vs IND 25m 54s",
    "19.5",
    "Points",
    "Less",
    "More",
    "CJ McCollum",
    "ATL - G",
    "CJ McCollum",
    "vs IND 25m 54s",
    "17.5",
    "Points",
    "Less",
    "More",
    "Trending",
    "8.3K",
    "Onyeka Okongwu",
    "ATL - F-C",
    "Onyeka Okongwu",
    "vs IND 25m 54s",
    "17",
    "Points",
    "Less",
    "More",
    "Andrew Nembhard",
    "IND - G-F",
    "Andrew Nembhard",
    "@ ATL 25m 54s",
    "16.5",
    "Points",
    "Less",
    "More",
    "Bennedict Mathurin",
    "IND - G-F",
    "Bennedict Mathurin",
    "@ ATL 25m 54s",
    "14.5",
    "Points",
    "Less",
    "More",
    "Aaron Nesmith",
    "IND - G-F",
    "Aaron Nesmith",
    "@ ATL 25m 54s",
    "13.5",
    "Points",
    "Less",
    "More",
    "Dyson Daniels",
    "ATL - G",
    "Dyson Daniels",
    "vs IND 25m 54s",
    "11.5",
    "Points",
    "Less",
    "More",
    "Jarace Walker",
    "IND - F",
    "Jarace Walker",
    "@ ATL 25m 54s",
    "10.5",
    "Points",
    "Less",
    "More",
    "Corey Kispert",
    "ATL - F",
    "Corey Kispert",
    "vs IND 25m 54s",
    "7.5",
    "Points",
    "Less",
    "More",
    "T.J. McConnell",
    "IND - G",
    "T.J. McConnell",
    "@ ATL 25m 54s",
    "8.5",
    "Points",
    "Less",
    "More",
    "Johnny Furphy",
    "IND - G",
    "Johnny Furphy",
    "@ ATL 25m 54s",
    "5.5",
    "Points",
    "Less",
    "More",
    "Luke Kennard",
    "ATL - G",
    "Luke Kennard",
    "vs IND 25m 54s",
    "7.5",
    "Points",
    "Less",
    "More",
    "Ben Sheppard",
    "IND - G",
    "Ben Sheppard",
    "@ ATL 25m 54s",
    "3.5",
    "Points",
    "Less",
    "More"
  ]
}