{
  "date": "2026-01-21",
  "timestamp": "2026-01-21T01:15:50.999044",
  "slate": "NOP DET UNDER22",
  "source_file": "NOP DET UNDER22_RISK_FIRST_20260121_FROM_UD.json",
  "summary": {
    "play_count": 0,
    "lean_count": 5,
    "total": 5
  },
  "picks": [
    {
      "player": "Zion Williamson",
      "team": "UNK",
      "stat": "pra",
      "line": 28.5,
      "direction": "higher",
      "decision": "LEAN",
      "probability": 68.0
    },
    {
      "player": "Duncan Robinson",
      "team": "UNK",
      "stat": "pra",
      "line": 15.5,
      "direction": "higher",
      "decision": "LEAN",
      "probability": 68.0
    },
    {
      "player": "Saddiq Bey",
      "team": "UNK",
      "stat": "pra",
      "line": 18.5,
      "direction": "higher",
      "decision": "LEAN",
      "probability": 68.0
    },
    {
      "player": "Duncan Robinson",
      "team": "UNK",
      "stat": "3pm",
      "line": 2.5,
      "direction": "higher",
      "decision": "LEAN",
      "probability": 67.2
    },
    {
      "player": "Derik Queen",
      "team": "UNK",
      "stat": "pra",
      "line": 21.5,
      "direction": "higher",
      "decision": "LEAN",
      "probability": 66.1
    }
  ]
}